exports/__init__.py
exports/_meta.py
exports/core.py
exports/py.typed
xports-0.0.1.dist-info/LICENSE
xports-0.0.1.dist-info/WHEEL
xports-0.0.1.dist-info/METADATA
xports-0.0.1.dist-info/RECORD
