Metadata-Version: 2.1
Name: xports
Version: 0.0.1
Summary: exports and __all__
Home-page: https://github.com/dynamic-graphics-inc/dgpy-libs
License: MIT
Keywords: exports,dgpy
Author: jesse
Author-email: jessekrubin@gmail.com
Requires-Python: >=3.6.1,<4.0.0
Classifier: Development Status :: 5 - Production/Stable
Classifier: Intended Audience :: Developers
Classifier: License :: OSI Approved :: MIT License
Classifier: Programming Language :: Python
Classifier: Programming Language :: Python :: 3
Classifier: Programming Language :: Python :: 3.6
Classifier: Programming Language :: Python :: 3.7
Classifier: Programming Language :: Python :: 3.8
Classifier: Programming Language :: Python :: 3.9
Classifier: Typing :: Typed
Project-URL: Repository, https://github.com/dynamic-graphics-inc/dgpy-libs
